ocean_qap/__init__.py
ocean_qap/qap.py
ocean_qap-0.0.2.dist-info/METADATA
ocean_qap-0.0.2.dist-info/WHEEL
ocean_qap-0.0.2.dist-info/top_level.txt
ocean_qap-0.0.2.dist-info/RECORD
